iwashi/__init__.py
iwashi/__main__.py
iwashi/helper.py
iwashi/iwashi.py
iwashi/throttle.py
iwashi/version.py
iwashi/visitor.py
iwashi/service/__init__.py
iwashi/service/bandcamp.py
iwashi/service/booth.py
iwashi/service/fanbox.py
iwashi/service/github.py
iwashi/service/instagram.py
iwashi/service/itchio.py
iwashi/service/kofi.py
iwashi/service/linktree.py
iwashi/service/litlink.py
iwashi/service/marshmallowqa.py
iwashi/service/mirrativ.py
iwashi/service/nicovideo.py
iwashi/service/note.py
iwashi/service/patreon.py
iwashi/service/pixiv.py
iwashi/service/reddit.py
iwashi/service/skeb.py
iwashi/service/sketch.py
iwashi/service/soundcloud.py
iwashi/service/spotify.py
iwashi/service/tiktok.py
iwashi/service/twitcasting.py
iwashi/service/twitch.py
iwashi/service/twitter.py
iwashi/service/youtube/__init__.py
iwashi/service/youtube/youtube.py
iwashi/service/youtube/types/__init__.py
iwashi/service/youtube/types/about.py
iwashi/service/youtube/types/ytinitialdata.py
iwashi/service/youtube/types/ytinitialdata2.py
iwashi/service/youtube/types/ytinitialdata3.py
iwashi-3.1.2.dist-info/METADATA
iwashi-3.1.2.dist-info/WHEEL
iwashi-3.1.2.dist-info/licenses/LICENSE
iwashi-3.1.2.dist-info/RECORD
