Metadata-Version: 2.4
Name: iwashi
Version: 3.1.2
Summary: Add your description here
Author-email: am230 <111672334+am230@users.noreply.github.com>
License-File: LICENSE
Requires-Python: >=3.8
Requires-Dist: aiohttp>=3.9.5
Requires-Dist: bs4>=0.0.2
Requires-Dist: click>=8.1.7
Requires-Dist: loguru>=0.7.2
